spacy_wrap/__init__.py
spacy_wrap/about.py
spacy_wrap/architectures.py
spacy_wrap/pipeline_component_seq_clf.py
spacy_wrap/pipeline_component_tok_clf.py
spacy_wrap/util.py
spacy_wrap/layers/__init__.py
spacy_wrap/layers/clf_transformer_model.py
spacy_wrap-1.4.5.dist-info/LICENSE
spacy_wrap-1.4.5.dist-info/METADATA
spacy_wrap-1.4.5.dist-info/WHEEL
spacy_wrap-1.4.5.dist-info/entry_points.txt
spacy_wrap-1.4.5.dist-info/top_level.txt
spacy_wrap-1.4.5.dist-info/RECORD
